Workbook

Sheet README
B1: PROJECT OVERVIEW
B5: Project Title :
C7: Client Profitability & Revenue Trend Analyis
B10: Objectives
C12: Analyze company revenue, COGS and profitability trends to identify key revenue drivers and the most profitable clients.
B15: Tools Used
C17: Microsoft Excel
C18: SUMIFS
C19: IF Functions
C20: Financial Analysis
C21: Data Visualization
B25: KPI's Analyzed
C27: Revenue
C28: COGS
C29: Gross Profit
C30: Gross Profit %
C31: Revenue Contribution %

Sheet 01-RAW-DATA
B1: Source Data Set : Raw transactional data containing monthly revenue and COGS information across different client types and customer accounts.
B3: Period | C3: Type of client | D3: Client name | E3: Revenue ($ 000') | F3: Cogs ($ 000')
B4: 42005 | C4: Supermarkets | D4: Kaufland | E4: 4680 | F4: 2569.32
B5: 42005 | C5: Supermarkets | D5: Aldi | E5: 2600 | F5: 1391
B6: 42005 | C6: Supermarkets | D6: Plus | E6: 3040 | F6: 1605.12
B7: 42005 | C7: Supermarkets | D7: Metro | E7: 1800 | F7: 882
B8: 42005 | C8: Supermarkets | D8: Carrefour | E8: 2840 | F8: 1533.6
B9: 42005 | C9: Supermarkets | D9: Esselunga | E9: 3320 | F9: 1593.6
B10: 42005 | C10: Supermarkets | D10: Billa | E10: 3120 | F10: 1404
B11: 42005 | C11: Supermarkets | D11: Costco | E11: 3360 | F11: 1811.04
B12: 42005 | C12: Fast Food | D12: McDonald's | E12: 1520 | F12: 820.8
B13: 42005 | C13: Fast Food | D13: Burger King | E13: 440 | F13: 268.4
B14: 42005 | C14: Fast Food | D14: KFC | E14: 760 | F14: 418
B15: 42005 | C15: Fast Food | D15: Subway | E15: 1800 | F15: 936
... B195: 42339 | C195: Other | D195: Other | E195: 3158.434 | F195: 1544.5105

Sheet 02-ANNUAL-FINANCIAL-PERFORMANCE
B1: Annual Revenue, COGS & Gross Profit Analysis
B3: Calculate total annual revenue, cost of goods sold (COGS), and gross profit to assess the company's overall financial performance for 2015.
B6: Total Revenue | C6: =SUM('01-RAW-DATA'!E4:E195) -> 524449.22
B7: COGS | C7: =SUM('01-RAW-DATA'!F4:F195) -> 272424.82
B8: Gross Profit | C8: =C6-C7 -> 252024.4

Sheet 03_Monthly_Performance_Analysis
B1: Monthly Revenue, COGS & Gross Profit Trends
B3: Analyze monthly revenue and COGS performance throughout the year and identify profitability trends using gross profit analysis and visualizations.
B4: Create an area chart that shows the development of Revenues and Cogs.
B6: MONTHLY SUMMARY
C8: Monthly | D8: Revenue | E8: COGS | F8: Gross profit
C9: 42005 | D9: =SUMIFS('01-RAW-DATA'!$E$4:$E$195,'01-RAW-DATA'!$B$4:$B$195,$C9) -> 40000 | E9: =SUMIFS('01-RAW-DATA'!$F$4:$F$195,'01-RAW-DATA'!$B$4:$B$195,$C9) -> 19552.48 | F9: =$D9-$E9 -> 20447.52
C10: 42036 | D10: =SUMIFS('01-RAW-DATA'!$E$4:$E$195,'01-RAW-DATA'!$B$4:$B$195,$C10) -> 44000 | E10: =SUMIFS('01-RAW-DATA'!$F$4:$F$195,'01-RAW-DATA'!$B$4:$B$195,$C10) -> 21978.051 | F10: =$D10-$E10 -> 22021.949
C11: 42064 | D11: =SUMIFS('01-RAW-DATA'!$E$4:$E$195,'01-RAW-DATA'!$B$4:$B$195,$C11) -> 43120 | E11: =SUMIFS('01-RAW-DATA'!$F$4:$F$195,'01-RAW-DATA'!$B$4:$B$195,$C11) -> 21729.518 | F11: =$D11-$E11 -> 21390.482
C12: 42095 | D12: =SUMIFS('01-RAW-DATA'!$E$4:$E$195,'01-RAW-DATA'!$B$4:$B$195,$C12) -> 41826.4 | E12: =SUMIFS('01-RAW-DATA'!$F$4:$F$195,'01-RAW-DATA'!$B$4:$B$195,$C12) -> 21278.121 | F12: =$D12-$E12 -> 20548.279
C13: 42125 | D13: =SUMIFS('01-RAW-DATA'!$E$4:$E$195,'01-RAW-DATA'!$B$4:$B$195,$C13) -> 38062.024 | E13: =SUMIFS('01-RAW-DATA'!$F$4:$F$195,'01-RAW-DATA'!$B$4:$B$195,$C13) -> 19416.407 | F13: =$D13-$E13 -> 18645.617
C14: 42156 | D14: =SUMIFS('01-RAW-DATA'!$E$4:$E$195,'01-RAW-DATA'!$B$4:$B$195,$C14) -> 40726.366 | E14: =SUMIFS('01-RAW-DATA'!$F$4:$F$195,'01-RAW-DATA'!$B$4:$B$195,$C14) -> 21432.956 | F14: =$D14-$E14 -> 19293.409
C15: 42186 | D15: =SUMIFS('01-RAW-DATA'!$E$4:$E$195,'01-RAW-DATA'!$B$4:$B$195,$C15) -> 42371.711 | E15: =SUMIFS('01-RAW-DATA'!$F$4:$F$195,'01-RAW-DATA'!$B$4:$B$195,$C15) -> 22417.635 | F15: =$D15-$E15 -> 19954.076
C16: 42217 | D16: =SUMIFS('01-RAW-DATA'!$E$4:$E$195,'01-RAW-DATA'!$B$4:$B$195,$C16) -> 43202.529 | E16: =SUMIFS('01-RAW-DATA'!$F$4:$F$195,'01-RAW-DATA'!$B$4:$B$195,$C16) -> 23460.956 | F16: =$D16-$E16 -> 19741.572
C17: 42248 | D17: =SUMIFS('01-RAW-DATA'!$E$4:$E$195,'01-RAW-DATA'!$B$4:$B$195,$C17) -> 47954.807 | E17: =SUMIFS('01-RAW-DATA'!$F$4:$F$195,'01-RAW-DATA'!$B$4:$B$195,$C17) -> 25981.449 | F17: =$D17-$E17 -> 21973.358
C18: 42278 | D18: =SUMIFS('01-RAW-DATA'!$E$4:$E$195,'01-RAW-DATA'!$B$4:$B$195,$C18) -> 47475.259 | E18: =SUMIFS('01-RAW-DATA'!$F$4:$F$195,'01-RAW-DATA'!$B$4:$B$195,$C18) -> 23984.946 | F18: =$D18-$E18 -> 23490.313
C19: 42309 | D19: =SUMIFS('01-RAW-DATA'!$E$4:$E$195,'01-RAW-DATA'!$B$4:$B$195,$C19) -> 45576.248 | E19: =SUMIFS('01-RAW-DATA'!$F$4:$F$195,'01-RAW-DATA'!$B$4:$B$195,$C19) -> 23879.022 | F19: =$D19-$E19 -> 21697.227
C20: 42339 | D20: =SUMIFS('01-RAW-DATA'!$E$4:$E$195,'01-RAW-DATA'!$B$4:$B$195,$C20) -> 50133.873 | E20: =SUMIFS('01-RAW-DATA'!$F$4:$F$195,'01-RAW-DATA'!$B$4:$B$195,$C20) -> 27313.275 | F20: =$D20-$E20 -> 22820.598

Sheet 04_Revenue_Mix_Analysis
B1: Revenue Contribution by Client Segment
B3: Evaluate how different client segments contributed to total revenue and determine the revenue distribution across Supermarkets, Fast Food, and Other client categories.
B4: Create a chart that shows the incidence on Revenues that different type of clients had throughout the year.
C8: Monthly Revenue Breakdown
C10: Month | D10: Supermarkets | E10: Fast Food | F10: Other | G10: Total Revnue | H10: %supermarkets | I10: %Fast Food | J10: %Others
C11: 42005 | D11: =SUMIFS('01-RAW-DATA'!$E$4:$E$195,'01-RAW-DATA'!$B$4:$B$195,$C11,'01-RAW-DATA'!$C$4:$C$195,D$10) -> 24760 | E11: =SUMIFS('01-RAW-DATA'!$E$4:$E$195,'01-RAW-DATA'!$B$4:$B$195,$C11,'01-RAW-DATA'!$C$4:$C$195,E$10) -> 4520 | F11: =SUMIFS('01-RAW-DATA'!$E$4:$E$195,'01-RAW-DATA'!$B$4:$B$195,$C11,'01-RAW-DATA'!$C$4:$C$195,F$10) -> 10720 | G11: =SUM($D11:$F11) -> 40000 | H11: =$D11/$G11 -> 0.619 | I11: =$E11/$G11 -> 0.113 | J11: =$F11/$G11 -> 0.268
C12: 42036 | D12: =SUMIFS('01-RAW-DATA'!$E$4:$E$195,'01-RAW-DATA'!$B$4:$B$195,$C12,'01-RAW-DATA'!$C$4:$C$195,D$10) -> 24596 | E12: =SUMIFS('01-RAW-DATA'!$E$4:$E$195,'01-RAW-DATA'!$B$4:$B$195,$C12,'01-RAW-DATA'!$C$4:$C$195,E$10) -> 5852 | F12: =SUMIFS('01-RAW-DATA'!$E$4:$E$195,'01-RAW-DATA'!$B$4:$B$195,$C12,'01-RAW-DATA'!$C$4:$C$195,F$10) -> 13552 | G12: =SUM($D12:$F12) -> 44000 | H12: =$D12/$G12 -> 0.559 | I12: =$E12/$G12 -> 0.133 | J12: =$F12/$G12 -> 0.308
C13: 42064 | D13: =SUMIFS('01-RAW-DATA'!$E$4:$E$195,'01-RAW-DATA'!$B$4:$B$195,$C13,'01-RAW-DATA'!$C$4:$C$195,D$10) -> 25828.88 | E13: =SUMIFS('01-RAW-DATA'!$E$4:$E$195,'01-RAW-DATA'!$B$4:$B$195,$C13,'01-RAW-DATA'!$C$4:$C$195,E$10) -> 4872.56 | F13: =SUMIFS('01-RAW-DATA'!$E$4:$E$195,'01-RAW-DATA'!$B$4:$B$195,$C13,'01-RAW-DATA'!$C$4:$C$195,F$10) -> 12418.56 | G13: =SUM($D13:$F13) -> 43120 | H13: =$D13/$G13 -> 0.599 | I13: =$E13/$G13 -> 0.113 | J13: =$F13/$G13 -> 0.288
C14: 42095 | D14: =SUMIFS('01-RAW-DATA'!$E$4:$E$195,'01-RAW-DATA'!$B$4:$B$195,$C14,'01-RAW-DATA'!$C$4:$C$195,D$10) -> 22126.166 | E14: =SUMIFS('01-RAW-DATA'!$E$4:$E$195,'01-RAW-DATA'!$B$4:$B$195,$C14,'01-RAW-DATA'!$C$4:$C$195,E$10) -> 6817.7032 | F14: =SUMIFS('01-RAW-DATA'!$E$4:$E$195,'01-RAW-DATA'!$B$4:$B$195,$C14,'01-RAW-DATA'!$C$4:$C$195,F$10) -> 12882.531 | G14: =SUM($D14:$F14) -> 41826.4 | H14: =$D14/$G14 -> 0.529 | I14: =$E14/$G14 -> 0.163 | J14: =$F14/$G14 -> 0.308
C15: 42125 | D15: =SUMIFS('01-RAW-DATA'!$E$4:$E$195,'01-RAW-DATA'!$B$4:$B$195,$C15,'01-RAW-DATA'!$C$4:$C$195,D$10) -> 19640.004 | E15: =SUMIFS('01-RAW-DATA'!$E$4:$E$195,'01-RAW-DATA'!$B$4:$B$195,$C15,'01-RAW-DATA'!$C$4:$C$195,E$10) -> 6318.296 | F15: =SUMIFS('01-RAW-DATA'!$E$4:$E$195,'01-RAW-DATA'!$B$4:$B$195,$C15,'01-RAW-DATA'!$C$4:$C$195,F$10) -> 12103.724 | G15: =SUM($D15:$F15) -> 38062.024 | H15: =$D15/$G15 -> 0.516 | I15: =$E15/$G15 -> 0.166 | J15: =$F15/$G15 -> 0.318
C16: 42156 | D16: =SUMIFS('01-RAW-DATA'!$E$4:$E$195,'01-RAW-DATA'!$B$4:$B$195,$C16,'01-RAW-DATA'!$C$4:$C$195,D$10) -> 23051.123 | E16: =SUMIFS('01-RAW-DATA'!$E$4:$E$195,'01-RAW-DATA'!$B$4:$B$195,$C16,'01-RAW-DATA'!$C$4:$C$195,E$10) -> 6353.313 | F16: =SUMIFS('01-RAW-DATA'!$E$4:$E$195,'01-RAW-DATA'!$B$4:$B$195,$C16,'01-RAW-DATA'!$C$4:$C$195,F$10) -> 11321.93 | G16: =SUM($D16:$F16) -> 40726.366 | H16: =$D16/$G16 -> 0.566 | I16: =$E16/$G16 -> 0.156 | J16: =$F16/$G16 -> 0.278
C17: 42186 | D17: =SUMIFS('01-RAW-DATA'!$E$4:$E$195,'01-RAW-DATA'!$B$4:$B$195,$C17,'01-RAW-DATA'!$C$4:$C$195,D$10) -> 25589.19 | E17: =SUMIFS('01-RAW-DATA'!$E$4:$E$195,'01-RAW-DATA'!$B$4:$B$195,$C17,'01-RAW-DATA'!$C$4:$C$195,E$10) -> 5234.1525 | F17: =SUMIFS('01-RAW-DATA'!$E$4:$E$195,'01-RAW-DATA'!$B$4:$B$195,$C17,'01-RAW-DATA'!$C$4:$C$195,F$10) -> 11548.368 | G17: =SUM($D17:$F17) -> 42371.711 | H17: =$D17/$G17 -> 0.60392157 | I17: =$E17/$G17 -> 0.12352941 | J17: =$F17/$G17 -> 0.27254902
C18: 42217 | D18: =SUMIFS('01-RAW-DATA'!$E$4:$E$195,'01-RAW-DATA'!$B$4:$B$195,$C18,'01-RAW-DATA'!$C$4:$C$195,D$10) -> 28772.884 | E18: =SUMIFS('01-RAW-DATA'!$E$4:$E$195,'01-RAW-DATA'!$B$4:$B$195,$C18,'01-RAW-DATA'!$C$4:$C$195,E$10) -> 5011.4933 | F18: =SUMIFS('01-RAW-DATA'!$E$4:$E$195,'01-RAW-DATA'!$B$4:$B$195,$C18,'01-RAW-DATA'!$C$4:$C$195,F$10) -> 9418.1513 | G18: =SUM($D18:$F18) -> 43202.529 | H18: =$D18/$G18 -> 0.666 | I18: =$E18/$G18 -> 0.116 | J18: =$F18/$G18 -> 0.218
C19: 42248 | D19: =SUMIFS('01-RAW-DATA'!$E$4:$E$195,'01-RAW-DATA'!$B$4:$B$195,$C19,'01-RAW-DATA'!$C$4:$C$195,D$10) -> 27621.969 | E19: =SUMIFS('01-RAW-DATA'!$E$4:$E$195,'01-RAW-DATA'!$B$4:$B$195,$C19,'01-RAW-DATA'!$C$4:$C$195,E$10) -> 8440.046 | F19: =SUMIFS('01-RAW-DATA'!$E$4:$E$195,'01-RAW-DATA'!$B$4:$B$195,$C19,'01-RAW-DATA'!$C$4:$C$195,F$10) -> 11892.792 | G19: =SUM($D19:$F19) -> 47954.807 | H19: =$D19/$G19 -> 0.576 | I19: =$E19/$G19 -> 0.176 | J19: =$F19/$G19 -> 0.248
C20: 42278 | D20: =SUMIFS('01-RAW-DATA'!$E$4:$E$195,'01-RAW-DATA'!$B$4:$B$195,$C20,'01-RAW-DATA'!$C$4:$C$195,D$10) -> 25446.739 | E20: =SUMIFS('01-RAW-DATA'!$E$4:$E$195,'01-RAW-DATA'!$B$4:$B$195,$C20,'01-RAW-DATA'!$C$4:$C$195,E$10) -> 9352.626 | F20: =SUMIFS('01-RAW-DATA'!$E$4:$E$195,'01-RAW-DATA'!$B$4:$B$195,$C20,'01-RAW-DATA'!$C$4:$C$195,F$10) -> 12675.894 | G20: =SUM($D20:$F20) -> 47475.259 | H20: =$D20/$G20 -> 0.536 | I20: =$E20/$G20 -> 0.197 | J20: =$F20/$G20 -> 0.267
C21: 42309 | D21: =SUMIFS('01-RAW-DATA'!$E$4:$E$195,'01-RAW-DATA'!$B$4:$B$195,$C21,'01-RAW-DATA'!$C$4:$C$195,D$10) -> 25340.394 | E21: =SUMIFS('01-RAW-DATA'!$E$4:$E$195,'01-RAW-DATA'!$B$4:$B$195,$C21,'01-RAW-DATA'!$C$4:$C$195,E$10) -> 9890.0459 | F21: =SUMIFS('01-RAW-DATA'!$E$4:$E$195,'01-RAW-DATA'!$B$4:$B$195,$C21,'01-RAW-DATA'!$C$4:$C$195,F$10) -> 10345.808 | G21: =SUM($D21:$F21) -> 45576.248 | H21: =$D21/$G21 -> 0.556 | I21: =$E21/$G21 -> 0.217 | J21: =$F21/$G21 -> 0.227
C22: 42339 | D22: =SUMIFS('01-RAW-DATA'!$E$4:$E$195,'01-RAW-DATA'!$B$4:$B$195,$C22,'01-RAW-DATA'!$C$4:$C$195,D$10) -> 24114.393 | E22: =SUMIFS('01-RAW-DATA'!$E$4:$E$195,'01-RAW-DATA'!$B$4:$B$195,$C22,'01-RAW-DATA'!$C$4:$C$195,E$10) -> 11380.389 | F22: =SUMIFS('01-RAW-DATA'!$E$4:$E$195,'01-RAW-DATA'!$B$4:$B$195,$C22,'01-RAW-DATA'!$C$4:$C$195,F$10) -> 14639.091 | G22: =SUM($D22:$F22) -> 50133.873 | H22: =$D22/$G22 -> 0.481 | I22: =$E22/$G22 -> 0.227 | J22: =$F22/$G22 -> 0.292

Sheet 05_Client_Profitability_Analysi
B1: Client Revenue, Gross Profit & Margin Analysis
B3: Assess the profitability of individual client accounts by comparing revenue, COGS, gross profit, and gross profit margins to identify the highest-performing customers.
B4: Create a column chart that shows the development of GP% of Kaufland and Aldi.
C6: ANNUAL REVENUE AND COGS BREAKDOWN FOR ALL CLIENT
C7: Client | D7: Revenue | E7: COGS | F7: Gross Profit | G7: GP%
C8: Kaufland | D8: =SUMIFS('01-RAW-DATA'!$E$4:$E$195,'01-RAW-DATA'!$D$4:$D$195,$C8) -> 66356.115 | E8: =SUMIFS('01-RAW-DATA'!$F$4:$F$195,'01-RAW-DATA'!$D$4:$D$195,$C8) -> 38588.783 | F8: =$D8-$E8 -> 27767.332 | G8: =$F8/$D8 -> 0.41845928
C9: Aldi | D9: =SUMIFS('01-RAW-DATA'!$E$4:$E$195,'01-RAW-DATA'!$D$4:$D$195,$C9) -> 44526.265 | E9: =SUMIFS('01-RAW-DATA'!$F$4:$F$195,'01-RAW-DATA'!$D$4:$D$195,$C9) -> 26807.78 | F9: =$D9-$E9 -> 17718.484 | G9: =$F9/$D9 -> 0.39793332
C10: Plus | D10: =SUMIFS('01-RAW-DATA'!$E$4:$E$195,'01-RAW-DATA'!$D$4:$D$195,$C10) -> 54921.168 | E10: =SUMIFS('01-RAW-DATA'!$F$4:$F$195,'01-RAW-DATA'!$D$4:$D$195,$C10) -> 27457.589 | F10: =$D10-$E10 -> 27463.579 | G10: =$F10/$D10 -> 0.50005453
C11: Metro | D11: =SUMIFS('01-RAW-DATA'!$E$4:$E$195,'01-RAW-DATA'!$D$4:$D$195,$C11) -> 28589.956 | E11: =SUMIFS('01-RAW-DATA'!$F$4:$F$195,'01-RAW-DATA'!$D$4:$D$195,$C11) -> 13047.779 | F11: =$D11-$E11 -> 15542.178 | G11: =$F11/$D11 -> 0.54362369
C12: Carrefour | D12: =SUMIFS('01-RAW-DATA'!$E$4:$E$195,'01-RAW-DATA'!$D$4:$D$195,$C12) -> 24412.624 | E12: =SUMIFS('01-RAW-DATA'!$F$4:$F$195,'01-RAW-DATA'!$D$4:$D$195,$C12) -> 12877.495 | F12: =$D12-$E12 -> 11535.129 | G12: =$F12/$D12 -> 0.47250672
C13: Esselunga | D13: =SUMIFS('01-RAW-DATA'!$E$4:$E$195,'01-RAW-DATA'!$D$4:$D$195,$C13) -> 32319.657 | E13: =SUMIFS('01-RAW-DATA'!$F$4:$F$195,'01-RAW-DATA'!$D$4:$D$195,$C13) -> 16821.6 | F13: =$D13-$E13 -> 15498.057 | G13: =$F13/$D13 -> 0.47952417
C14: Billa | D14: =SUMIFS('01-RAW-DATA'!$E$4:$E$195,'01-RAW-DATA'!$D$4:$D$195,$C14) -> 23156.108 | E14: =SUMIFS('01-RAW-DATA'!$F$4:$F$195,'01-RAW-DATA'!$D$4:$D$195,$C14) -> 11159.525 | F14: =$D14-$E14 -> 11996.583 | G14: =$F14/$D14 -> 0.51807426
C15: Costco | D15: =SUMIFS('01-RAW-DATA'!$E$4:$E$195,'01-RAW-DATA'!$D$4:$D$195,$C15) -> 22605.848 | E15: =SUMIFS('01-RAW-DATA'!$F$4:$F$195,'01-RAW-DATA'!$D$4:$D$195,$C15) -> 12615.723 | F15: =$D15-$E15 -> 9990.1248 | G15: =$F15/$D15 -> 0.44192657
C16: McDonald's | D16: =SUMIFS('01-RAW-DATA'!$E$4:$E$195,'01-RAW-DATA'!$D$4:$D$195,$C16) -> 24974.207 | E16: =SUMIFS('01-RAW-DATA'!$F$4:$F$195,'01-RAW-DATA'!$D$4:$D$195,$C16) -> 14559.695 | F16: =$D16-$E16 -> 10414.513 | G16: =$F16/$D16 -> 0.41701074
C17: Burger King | D17: =SUMIFS('01-RAW-DATA'!$E$4:$E$195,'01-RAW-DATA'!$D$4:$D$195,$C17) -> 11853.232 | E17: =SUMIFS('01-RAW-DATA'!$F$4:$F$195,'01-RAW-DATA'!$D$4:$D$195,$C17) -> 7378.9089 | F17: =$D17-$E17 -> 4474.3231 | G17: =$F17/$D17 -> 0.37747706
C18: KFC | D18: =SUMIFS('01-RAW-DATA'!$E$4:$E$195,'01-RAW-DATA'!$D$4:$D$195,$C18) -> 27237.485 | E18: =SUMIFS('01-RAW-DATA'!$F$4:$F$195,'01-RAW-DATA'!$D$4:$D$195,$C18) -> 15851.521 | F18: =$D18-$E18 -> 11385.964 | G18: =$F18/$D18 -> 0.41802553
C19: Subway | D19: =SUMIFS('01-RAW-DATA'!$E$4:$E$195,'01-RAW-DATA'!$D$4:$D$195,$C19) -> 19977.701 | E19: =SUMIFS('01-RAW-DATA'!$F$4:$F$195,'01-RAW-DATA'!$D$4:$D$195,$C19) -> 11147.659 | F19: =$D19-$E19 -> 8830.0415 | G19: =$F19/$D19 -> 0.44199488
... C23: Other | D23: =SUMIFS('01-RAW-DATA'!$E$4:$E$195,'01-RAW-DATA'!$D$4:$D$195,$C23) -> 40584.052 | E23: =SUMIFS('01-RAW-DATA'!$F$4:$F$195,'01-RAW-DATA'!$D$4:$D$195,$C23) -> 17686.435 | F23: =$D23-$E23 -> 22897.616 | G23: =$F23/$D23 -> 0.56420233
C27: Monthly Revenue and COGS breakdown for ALDI and KAUFLAND
D28: Aldi | E28: Aldi | H28: Kaufland | I28: Kaufland
C29: Months | D29: ALDIS REV | E29: ALDI COGS | F29: Gross Profit | G29: GP% | H29: KAUFLAND REV | I29: KAUFLAND COGS | J29: Gross Profit | K29: GP% | O29: Key Insights
C30: 42005 | D30: =SUMIFS('01-RAW-DATA'!$E$4:$E$195,'01-RAW-DATA'!$B$4:$B$195,$C30,'01-RAW-DATA'!$D$4:$D$195,D$28) -> 2600 | E30: =SUMIFS('01-RAW-DATA'!$F$4:$F$195,'01-RAW-DATA'!$B$4:$B$195,$C30,'01-RAW-DATA'!$D$4:$D$195,E$28) -> 1391 | F30: =$D30-$E30 -> 1209 | G30: =$F30/$D30 -> 0.465 | H30: =SUMIFS('01-RAW-DATA'!$E$4:$E$195,'01-RAW-DATA'!$B$4:$B$195,$C30,'01-RAW-DATA'!$D$4:$D$195,H$28) -> 4680 | I30: =SUMIFS('01-RAW-DATA'!$F$4:$F$195,'01-RAW-DATA'!$B$4:$B$195,$C30,'01-RAW-DATA'!$D$4:$D$195,I$28) -> 2569.32 | J30: =$H30-$I30 -> 2110.68 | K30: =$J30/$H30 -> 0.451
C31: 42036 | D31: =SUMIFS('01-RAW-DATA'!$E$4:$E$195,'01-RAW-DATA'!$B$4:$B$195,$C31,'01-RAW-DATA'!$D$4:$D$195,D$28) -> 1980 | E31: =SUMIFS('01-RAW-DATA'!$F$4:$F$195,'01-RAW-DATA'!$B$4:$B$195,$C31,'01-RAW-DATA'!$D$4:$D$195,E$28) -> 1101.672 | F31: =$D31-$E31 -> 878.328 | G31: =$F31/$D31 -> 0.4436 | H31: =SUMIFS('01-RAW-DATA'!$E$4:$E$195,'01-RAW-DATA'!$B$4:$B$195,$C31,'01-RAW-DATA'!$D$4:$D$195,H$28) -> 4268 | I31: =SUMIFS('01-RAW-DATA'!$F$4:$F$195,'01-RAW-DATA'!$B$4:$B$195,$C31,'01-RAW-DATA'!$D$4:$D$195,I$28) -> 2577.4452 | J31: =$H31-$I31 -> 1690.5548 | K31: =$J31/$H31 -> 0.3961 | N31: Restaurants generated the highest GP% (59%).
C32: 42064 | D32: =SUMIFS('01-RAW-DATA'!$E$4:$E$195,'01-RAW-DATA'!$B$4:$B$195,$C32,'01-RAW-DATA'!$D$4:$D$195,D$28) -> 2802.8 | E32: =SUMIFS('01-RAW-DATA'!$F$4:$F$195,'01-RAW-DATA'!$B$4:$B$195,$C32,'01-RAW-DATA'!$D$4:$D$195,E$28) -> 1621.857 | F32: =$D32-$E32 -> 1180.943 | G32: =$F32/$D32 -> 0.421344 | H32: =SUMIFS('01-RAW-DATA'!$E$4:$E$195,'01-RAW-DATA'!$B$4:$B$195,$C32,'01-RAW-DATA'!$D$4:$D$195,H$28) -> 5045.04 | I32: =SUMIFS('01-RAW-DATA'!$F$4:$F$195,'01-RAW-DATA'!$B$4:$B$195,$C32,'01-RAW-DATA'!$D$4:$D$195,I$28) -> 2955.2987 | J32: =$H32-$I32 -> 2089.7413 | K32: =$J32/$H32 -> 0.414217 | N32: Metro achieved a GP% of 54%.
C33: 42095 | D33: =SUMIFS('01-RAW-DATA'!$E$4:$E$195,'01-RAW-DATA'!$B$4:$B$195,$C33,'01-RAW-DATA'!$D$4:$D$195,D$28) -> 3136.98 | E33: =SUMIFS('01-RAW-DATA'!$F$4:$F$195,'01-RAW-DATA'!$B$4:$B$195,$C33,'01-RAW-DATA'!$D$4:$D$195,E$28) -> 1851.5369 | F33: =$D33-$E33 -> 1285.4431 | G33: =$F33/$D33 -> 0.40977088 | H33: =SUMIFS('01-RAW-DATA'!$E$4:$E$195,'01-RAW-DATA'!$B$4:$B$195,$C33,'01-RAW-DATA'!$D$4:$D$195,H$28) -> 5730.2168 | I33: =SUMIFS('01-RAW-DATA'!$F$4:$F$195,'01-RAW-DATA'!$B$4:$B$195,$C33,'01-RAW-DATA'!$D$4:$D$195,I$28) -> 3255.9637 | J33: =$H33-$I33 -> 2474.2531 | K33: =$J33/$H33 -> 0.43179049 | N33: Aldi's GP% declined from 47% to 34% during the year.
C34: 42125 | D34: =SUMIFS('01-RAW-DATA'!$E$4:$E$195,'01-RAW-DATA'!$B$4:$B$195,$C34,'01-RAW-DATA'!$D$4:$D$195,D$28) -> 1712.7911 | E34: =SUMIFS('01-RAW-DATA'!$F$4:$F$195,'01-RAW-DATA'!$B$4:$B$195,$C34,'01-RAW-DATA'!$D$4:$D$195,E$28) -> 1031.158 | F34: =$D34-$E34 -> 681.63312 | G34: =$F34/$D34 -> 0.3979663 | H34: =SUMIFS('01-RAW-DATA'!$E$4:$E$195,'01-RAW-DATA'!$B$4:$B$195,$C34,'01-RAW-DATA'!$D$4:$D$195,H$28) -> 5290.6213 | I34: =SUMIFS('01-RAW-DATA'!$F$4:$F$195,'01-RAW-DATA'!$B$4:$B$195,$C34,'01-RAW-DATA'!$D$4:$D$195,I$28) -> 2946.0577 | J34: =$H34-$I34 -> 2344.5636 | K34: =$J34/$H34 -> 0.44315468 | N34: Kaufland maintained a relatively stable GP% between 39% and 45%.
C35: 42156 | D35: =SUMIFS('01-RAW-DATA'!$E$4:$E$195,'01-RAW-DATA'!$B$4:$B$195,$C35,'01-RAW-DATA'!$D$4:$D$195,D$28) -> 3461.7411 | E35: =SUMIFS('01-RAW-DATA'!$F$4:$F$195,'01-RAW-DATA'!$B$4:$B$195,$C35,'01-RAW-DATA'!$D$4:$D$195,E$28) -> 2042.4031 | F35: =$D35-$E35 -> 1419.338 | G35: =$F35/$D35 -> 0.41000697 | H35: =SUMIFS('01-RAW-DATA'!$E$4:$E$195,'01-RAW-DATA'!$B$4:$B$195,$C35,'01-RAW-DATA'!$D$4:$D$195,H$28) -> 6475.4921 | I35: =SUMIFS('01-RAW-DATA'!$F$4:$F$195,'01-RAW-DATA'!$B$4:$B$195,$C35,'01-RAW-DATA'!$D$4:$D$195,I$28) -> 3750.0814 | J35: =$H35-$I35 -> 2725.4108 | K35: =$J35/$H35 -> 0.42088087
C36: 42186 | D36: =SUMIFS('01-RAW-DATA'!$E$4:$E$195,'01-RAW-DATA'!$B$4:$B$195,$C36,'01-RAW-DATA'!$D$4:$D$195,D$28) -> 4361.7938 | E36: =SUMIFS('01-RAW-DATA'!$F$4:$F$195,'01-RAW-DATA'!$B$4:$B$195,$C36,'01-RAW-DATA'!$D$4:$D$195,E$28) -> 2676.365 | F36: =$D36-$E36 -> 1685.4287 | G36: =$F36/$D36 -> 0.38640725 | H36: =SUMIFS('01-RAW-DATA'!$E$4:$E$195,'01-RAW-DATA'!$B$4:$B$195,$C36,'01-RAW-DATA'!$D$4:$D$195,H$28) -> 5774.1841 | I36: =SUMIFS('01-RAW-DATA'!$F$4:$F$195,'01-RAW-DATA'!$B$4:$B$195,$C36,'01-RAW-DATA'!$D$4:$D$195,I$28) -> 3377.3799 | J36: =$H36-$I36 -> 2396.8042 | K36: =$J36/$H36 -> 0.41508968
C37: 42217 | D37: =SUMIFS('01-RAW-DATA'!$E$4:$E$195,'01-RAW-DATA'!$B$4:$B$195,$C37,'01-RAW-DATA'!$D$4:$D$195,D$28) -> 5400.3161 | E37: =SUMIFS('01-RAW-DATA'!$F$4:$F$195,'01-RAW-DATA'!$B$4:$B$195,$C37,'01-RAW-DATA'!$D$4:$D$195,E$28) -> 3446.1386 | F37: =$D37-$E37 -> 1954.1775 | G37: =$F37/$D37 -> 0.36186354 | H37: =SUMIFS('01-RAW-DATA'!$E$4:$E$195,'01-RAW-DATA'!$B$4:$B$195,$C37,'01-RAW-DATA'!$D$4:$D$195,H$28) -> 6869.2021 | I37: =SUMIFS('01-RAW-DATA'!$F$4:$F$195,'01-RAW-DATA'!$B$4:$B$195,$C37,'01-RAW-DATA'!$D$4:$D$195,I$28) -> 4098.2245 | J37: =$H37-$I37 -> 2770.9775 | K37: =$J37/$H37 -> 0.40339147
C38: 42248 | D38: =SUMIFS('01-RAW-DATA'!$E$4:$E$195,'01-RAW-DATA'!$B$4:$B$195,$C38,'01-RAW-DATA'!$D$4:$D$195,D$28) -> 4555.7067 | E38: =SUMIFS('01-RAW-DATA'!$F$4:$F$195,'01-RAW-DATA'!$B$4:$B$195,$C38,'01-RAW-DATA'!$D$4:$D$195,E$28) -> 2819.9476 | F38: =$D38-$E38 -> 1735.759 | G38: =$F38/$D38 -> 0.38100763 | H38: =SUMIFS('01-RAW-DATA'!$E$4:$E$195,'01-RAW-DATA'!$B$4:$B$195,$C38,'01-RAW-DATA'!$D$4:$D$195,H$28) -> 4747.5259 | I38: =SUMIFS('01-RAW-DATA'!$F$4:$F$195,'01-RAW-DATA'!$B$4:$B$195,$C38,'01-RAW-DATA'!$D$4:$D$195,I$28) -> 2775.7661 | J38: =$H38-$I38 -> 1971.7597 | K38: =$J38/$H38 -> 0.41532364
C39: 42278 | D39: =SUMIFS('01-RAW-DATA'!$E$4:$E$195,'01-RAW-DATA'!$B$4:$B$195,$C39,'01-RAW-DATA'!$D$4:$D$195,D$28) -> 4510.1496 | E39: =SUMIFS('01-RAW-DATA'!$F$4:$F$195,'01-RAW-DATA'!$B$4:$B$195,$C39,'01-RAW-DATA'!$D$4:$D$195,E$28) -> 2509.4472 | F39: =$D39-$E39 -> 2000.7024 | G39: =$F39/$D39 -> 0.4436 | H39: =SUMIFS('01-RAW-DATA'!$E$4:$E$195,'01-RAW-DATA'!$B$4:$B$195,$C39,'01-RAW-DATA'!$D$4:$D$195,H$28) -> 5174.8032 | I39: =SUMIFS('01-RAW-DATA'!$F$4:$F$195,'01-RAW-DATA'!$B$4:$B$195,$C39,'01-RAW-DATA'!$D$4:$D$195,I$28) -> 3125.0637 | J39: =$H39-$I39 -> 2049.7396 | K39: =$J39/$H39 -> 0.3961
C40: 42309 | D40: =SUMIFS('01-RAW-DATA'!$E$4:$E$195,'01-RAW-DATA'!$B$4:$B$195,$C40,'01-RAW-DATA'!$D$4:$D$195,D$28) -> 5241.2686 | E40: =SUMIFS('01-RAW-DATA'!$F$4:$F$195,'01-RAW-DATA'!$B$4:$B$195,$C40,'01-RAW-DATA'!$D$4:$D$195,E$28) -> 3155.4203 | F40: =$D40-$E40 -> 2085.8482 | G40: =$F40/$D40 -> 0.3979663 | H40: =SUMIFS('01-RAW-DATA'!$E$4:$E$195,'01-RAW-DATA'!$B$4:$B$195,$C40,'01-RAW-DATA'!$D$4:$D$195,H$28) -> 6335.0985 | I40: =SUMIFS('01-RAW-DATA'!$F$4:$F$195,'01-RAW-DATA'!$B$4:$B$195,$C40,'01-RAW-DATA'!$D$4:$D$195,I$28) -> 3527.67 | J40: =$H40-$I40 -> 2807.4286 | K40: =$J40/$H40 -> 0.44315468
C41: 42339 | D41: =SUMIFS('01-RAW-DATA'!$E$4:$E$195,'01-RAW-DATA'!$B$4:$B$195,$C41,'01-RAW-DATA'!$D$4:$D$195,D$28) -> 4762.718 | E41: =SUMIFS('01-RAW-DATA'!$F$4:$F$195,'01-RAW-DATA'!$B$4:$B$195,$C41,'01-RAW-DATA'!$D$4:$D$195,E$28) -> 3160.8345 | F41: =$D41-$E41 -> 1601.8834 | G41: =$F41/$D41 -> 0.33633808 | H41: =SUMIFS('01-RAW-DATA'!$E$4:$E$195,'01-RAW-DATA'!$B$4:$B$195,$C41,'01-RAW-DATA'!$D$4:$D$195,H$28) -> 5965.9309 | I41: =SUMIFS('01-RAW-DATA'!$F$4:$F$195,'01-RAW-DATA'!$B$4:$B$195,$C41,'01-RAW-DATA'!$D$4:$D$195,I$28) -> 3630.5118 | J41: =$H41-$I41 -> 2335.4191 | K41: =$J41/$H41 -> 0.3914593
